<?xml version="1.0" encoding="UTF-8" ?>
<poses>
	<pose>
		<id>00000-cam0</id>
		<translation>
			<x>0.2305831470243751568638402</x>
			<y>0.2032012107650197352270993</y>
			<z>1.815979263208065352941389</z>
		</translation>
		<rotation>
			<w>-0.423826922897553914904023</w>
			<x>0.5554320030122179563392137</x>
			<y>0.4304859239380930402418812</y>
			<z>0.5714436969187716153228962</z>
		</rotation>
	</pose>
	<pose>
		<id>00000-cam1</id>
		<translation>
			<x>0.3111438502212245937883495</x>
			<y>-0.003935068443289644474214484</y>
			<z>1.820489118095065084190765</z>
		</translation>
		<rotation>
			<w>0.00327365708126343664743918</w>
			<x>0.6990567044684733444270819</x>
			<y>-0.01200379198310008027617002</y>
			<z>0.7149579820416152031725687</z>
		</rotation>
	</pose>
	<pose>
		<id>00000-cam2</id>
		<translation>
			<x>0.2302526867493655537977304</x>
			<y>-0.2097499353145682032817376</y>
			<z>1.827863845425562683288945</z>
		</translation>
		<rotation>
			<w>0.4373867970275655547851557</w>
			<x>0.5462739773289069233896953</x>
			<y>-0.438182508306587892299433</y>
			<z>0.5641574433554615852770553</z>
		</rotation>
	</pose>
	<pose>
		<id>00000-cam3</id>
		<translation>
			<x>-0.01220985637302712811802508</x>
			<y>-0.1780672051268883393504439</y>
			<z>1.821403429535764617597238</z>
		</translation>
		<rotation>
			<w>0.6813594802454230325849949</w>
			<x>0.1795383126123229200477027</x>
			<y>-0.6866894041457203279321675</y>
			<z>0.1788097179070600728501006</z>
		</rotation>
	</pose>
	<pose>
		<id>00000-cam4</id>
		<translation>
			<x>-0.008666216111515856468372476</x>
			<y>0.17742447983584719306549</y>
			<z>1.821284862319189068458059</z>
		</translation>
		<rotation>
			<w>0.681428717609421918943724</w>
			<x>-0.1847464158562263092377975</x>
			<y>-0.6825092601839055639345588</y>
			<z>-0.1889570702796667112099982</z>
		</rotation>
	</pose>
	<pose>
		<id>00000-cam5</id>
		<translation>
			<x>0.1144663036451233906198865</x>
			<y>-0.0009333200837985770881299885</y>
			<z>1.921930239756107994253398</z>
		</translation>
		<rotation>
			<w>0.7044490463050384621013222</w>
			<x>-0.002653822911968039405250508</x>
			<y>-0.001441609183574090987181582</y>
			<z>-0.7097481385300250522618626</z>
		</rotation>
	</pose>
	<pose>
		<id>00001-cam0</id>
		<translation>
			<x>-0.05906781354282067408867363</x>
			<y>0.2800919694730029108065139</y>
			<z>1.810735807047030299088419</z>
		</translation>
		<rotation>
			<w>0.7029207088373211620435654</w>
			<x>-0.08436831134557577771548864</x>
			<y>-0.7007042119361378551545272</y>
			<z>-0.08830669549490127723245791</z>
		</rotation>
	</pose>
	<pose>
		<id>00001-cam1</id>
		<translation>
			<x>0.1456587613477835219111256</x>
			<y>0.3666234937461247955781118</y>
			<z>1.814625368570950580959789</z>
		</translation>
		<rotation>
			<w>0.5049724233586664334794136</w>
			<x>-0.4991638249795503634587135</x>
			<y>-0.4984903012864994598096757</y>
			<z>-0.497338664228475613171554</z>
		</rotation>
	</pose>
	<pose>
		<id>00001-cam2</id>
		<translation>
			<x>0.3536674143058587960197769</x>
			<y>0.2918072537372750629991458</y>
			<z>1.82424081839018970008226</z>
		</translation>
		<rotation>
			<w>-0.09344567391724453719881183</w>
			<x>0.6942388464270899950392391</x>
			<y>0.09283963542396567181214095</y>
			<z>0.7075882504662881489210235</z>
		</rotation>
	</pose>
	<pose>
		<id>00001-cam3</id>
		<translation>
			<x>0.3289580524330770749941166</x>
			<y>0.04846002475295965727930536</y>
			<z>1.821962495218670818886153</z>
		</translation>
		<rotation>
			<w>0.3512715195412740021296827</w>
			<x>0.6131484326048161070943365</x>
			<y>-0.3451488163753824167656603</y>
			<z>0.6176808347875244464830757</z>
		</rotation>
	</pose>
	<pose>
		<id>00001-cam4</id>
		<translation>
			<x>-0.02648564051419863285552481</x>
			<y>0.04181050453694834523332702</y>
			<z>1.820389431297060323089454</z>
		</translation>
		<rotation>
			<w>0.6122189483661859554786133</w>
			<x>0.35452707537432087692153</x>
			<y>-0.6063170867793352680763519</y>
			<z>0.3631502475870124757584279</z>
		</rotation>
	</pose>
	<pose>
		<id>00001-cam5</id>
		<translation>
			<x>0.1478324110494514675995248</x>
			<y>0.1717603494298523825190017</y>
			<z>1.919530083494962902079806</z>
		</translation>
		<rotation>
			<w>0.9998846471029491089765884</w>
			<x>-0.00965687368509192921306461</x>
			<y>-0.005025152459698660825648808</y>
			<z>0.01059174620652615812776975</z>
		</rotation>
	</pose>
	<pose>
		<id>00002-cam0</id>
		<translation>
			<x>-0.2107149133388907524810918</x>
			<y>0.07170580623864517000320973</y>
			<z>1.815098718917255160576474</z>
		</translation>
		<rotation>
			<w>0.5777584325476904369978115</w>
			<x>0.4153228086504310301307896</x>
			<y>-0.5638988047674712289492049</y>
			<z>0.4191900480197045530950106</z>
		</rotation>
	</pose>
	<pose>
		<id>00002-cam1</id>
		<translation>
			<x>-0.2840560773126183935488598</x>
			<y>0.2815504771047048215848463</y>
			<z>1.816544972558215675917381</z>
		</translation>
		<rotation>
			<w>0.7106811422510193043677873</w>
			<x>-0.0278730483958646337028231</x>
			<y>-0.7028572387976961266531362</y>
			<z>-0.01212885755434551550424604</z>
		</rotation>
	</pose>
	<pose>
		<id>00002-cam2</id>
		<translation>
			<x>-0.1961322987184599409005159</x>
			<y>0.4844995502353083294266867</y>
			<z>1.822758606583812168722147</z>
		</translation>
		<rotation>
			<w>0.5510133055949322233857401</w>
			<x>-0.4480289237871685203984384</x>
			<y>-0.5440866953353287183148268</y>
			<z>-0.4467931161315989996296594</z>
		</rotation>
	</pose>
	<pose>
		<id>00002-cam3</id>
		<translation>
			<x>0.04513688544332788987745175</x>
			<y>0.4443508116572766342144973</y>
			<z>1.819460611743674682827532</z>
		</translation>
		<rotation>
			<w>-0.1623079429753843672123992</w>
			<x>0.6866952217576539618804077</x>
			<y>0.1721485783581345185844214</y>
			<z>0.6873650202993072388935047</z>
		</rotation>
	</pose>
	<pose>
		<id>00002-cam4</id>
		<translation>
			<x>0.029211709619032882878642</x>
			<y>0.08921535100940944373881791</y>
			<z>1.822939539022946808799475</z>
		</translation>
		<rotation>
			<w>0.203272723909286912036265</w>
			<x>0.674259936756438471583408</x>
			<y>-0.1941157916210952960600622</y>
			<z>0.6829149265794571821430736</z>
		</rotation>
	</pose>
	<pose>
		<id>00002-cam5</id>
		<translation>
			<x>-0.08876540379552906590010508</x>
			<y>0.2728012088712725713435248</y>
			<z>1.920306102762684430373952</z>
		</translation>
		<rotation>
			<w>0.7218640326060625778126223</w>
			<x>-0.00636778754958574905870039</x>
			<y>-0.003090740208842178166764869</y>
			<z>0.6919987118605497311563113</z>
		</rotation>
	</pose>
	<pose>
		<id>00003-cam0</id>
		<translation>
			<x>0.03087849402050610314596213</x>
			<y>-0.1282163316519093765322168</y>
			<z>1.81591944518567460775671</z>
		</translation>
		<rotation>
			<w>0.1318687834217341092735154</w>
			<x>0.6905191705741418051189839</x>
			<y>-0.1202381674217394835757489</y>
			<z>0.7009541226740575448062032</z>
		</rotation>
	</pose>
	<pose>
		<id>00003-cam1</id>
		<translation>
			<x>-0.1823717642705600383568054</x>
			<y>-0.1909335360697037853316971</y>
			<z>1.81850468367738526964672</z>
		</translation>
		<rotation>
			<w>0.5255768286906037367600675</w>
			<x>0.4636544851418136214959986</x>
			<y>-0.5262211131668281804962817</y>
			<z>0.4815442404975197043803803</z>
		</rotation>
	</pose>
	<pose>
		<id>00003-cam2</id>
		<translation>
			<x>-0.3806338159444128121933204</x>
			<y>-0.09291093953696780149975609</y>
			<z>1.824927750366985179653057</z>
		</translation>
		<rotation>
			<w>0.7086301714352394309770489</w>
			<x>0.04849309186717025432766803</x>
			<y>-0.7015350558948960646432624</y>
			<z>0.05779503001484690566380564</z>
		</rotation>
	</pose>
	<pose>
		<id>00003-cam3</id>
		<translation>
			<x>-0.3284544365658268461061198</x>
			<y>0.146019945204597184629236</y>
			<z>1.820135896823064758365263</z>
		</translation>
		<rotation>
			<w>0.5913966730963932105780145</w>
			<x>-0.3812808604095257458688195</x>
			<y>-0.5979194293505566415447561</y>
			<z>-0.3838844051275331348271891</z>
		</rotation>
	</pose>
	<pose>
		<id>00003-cam4</id>
		<translation>
			<x>0.02544686558911729568066562</x>
			<y>0.1123255330214333325145049</y>
			<z>1.822473508478377635100287</z>
		</translation>
		<rotation>
			<w>-0.3222517642772893542435497</w>
			<x>0.6244182215616767006594046</x>
			<y>0.325127448225481729959796</y>
			<z>0.6328884794147521253293576</z>
		</rotation>
	</pose>
	<pose>
		<id>00003-cam5</id>
		<translation>
			<x>-0.1634561889697117575970253</x>
			<y>0.004233715455505649566392279</y>
			<z>1.921136617903419052666436</z>
		</translation>
		<rotation>
			<w>0.04618639272940440465564649</w>
			<x>-0.0007404569103596729670244136</x>
			<y>-0.003827223586342515596059322</y>
			<z>0.9989252330284743575106177</z>
		</rotation>
	</pose>
	<pose>
		<id>00004-cam0</id>
		<translation>
			<x>0.03824393407460011107268372</x>
			<y>-0.1241616213822241271413915</y>
			<z>1.817083570927036761943896</z>
		</translation>
		<rotation>
			<w>0.1247613763667561742609635</w>
			<x>0.6907626772715135254898655</x>
			<y>-0.111556458122603285865182</y>
			<z>0.7034462874232964013643254</z>
		</rotation>
	</pose>
	<pose>
		<id>00004-cam1</id>
		<translation>
			<x>-0.1735360025102818393172299</x>
			<y>-0.19168979286704465603286</y>
			<z>1.819321509183275731302842</z>
		</translation>
		<rotation>
			<w>0.5200909844501639955893779</w>
			<x>0.4682221533114529488095457</x>
			<y>-0.5208971788556627791066944</y>
			<z>0.4888143942960059273872275</z>
		</rotation>
	</pose>
	<pose>
		<id>00004-cam2</id>
		<translation>
			<x>-0.3739844986261563475338221</x>
			<y>-0.09816934703232570169628701</y>
			<z>1.824965352620950387318999</z>
		</translation>
		<rotation>
			<w>0.7071144468631496149413351</w>
			<x>0.05534468080043160320702356</x>
			<y>-0.7017483430834842161871734</y>
			<z>0.06689834308254385963898869</z>
		</rotation>
	</pose>
	<pose>
		<id>00004-cam3</id>
		<translation>
			<x>-0.3272216870138362487807626</x>
			<y>0.1418684270097789745790351</y>
			<z>1.819605906567538733398237</z>
		</translation>
		<rotation>
			<w>0.5944044606755376491946663</w>
			<x>-0.3748494158645130358564757</x>
			<y>-0.6035015703966080113929138</y>
			<z>-0.3767719563082111977614375</z>
		</rotation>
	</pose>
	<pose>
		<id>00004-cam4</id>
		<translation>
			<x>0.02734525218712743899196482</x>
			<y>0.1162130417971679319233402</y>
			<z>1.822921980888347226468227</z>
		</translation>
		<rotation>
			<w>-0.3280920536656592445545755</w>
			<x>0.6203600421830327560357432</x>
			<y>0.3335042819891460008641104</y>
			<z>0.6295108547575145596653101</z>
		</rotation>
	</pose>
	<pose>
		<id>00004-cam5</id>
		<translation>
			<x>-0.1593106612632756713399118</x>
			<y>0.00414904309315754921128061</y>
			<z>1.921430073847768982275852</z>
		</translation>
		<rotation>
			<w>0.03485486033222030821665527</w>
			<x>-0.002022358379259271265321329</x>
			<y>-0.002449887266265602867032491</y>
			<z>0.9993873357279383640161541</z>
		</rotation>
	</pose>
	<pose>
		<id>00005-cam0</id>
		<translation>
			<x>-0.2970606538984389421997889</x>
			<y>0.4739619271692748769808645</y>
			<z>1.813935389748645654606207</z>
		</translation>
		<rotation>
			<w>-0.4212205408455730326622302</w>
			<x>0.5601912426957076363009946</x>
			<y>0.4267740452569876996591347</y>
			<z>0.5715093541419834499706099</z>
		</rotation>
	</pose>
	<pose>
		<id>00005-cam1</id>
		<translation>
			<x>-0.218807946744140224826225</x>
			<y>0.2659438008895713689838658</y>
			<z>1.818493549140333120917035</z>
		</translation>
		<rotation>
			<w>0.00825430311514026987529391</w>
			<x>0.7012106663577601928238892</x>
			<y>-0.01498692735792815297624081</y>
			<z>0.7127488055932162946959352</z>
		</rotation>
	</pose>
	<pose>
		<id>00005-cam2</id>
		<translation>
			<x>-0.3019608443754210336251731</x>
			<y>0.06107293466793611846910039</y>
			<z>1.826922673969795241077918</z>
		</translation>
		<rotation>
			<w>0.4426442278716585243536485</w>
			<x>0.5449891506751144421016875</x>
			<y>-0.4391343102989195279484136</y>
			<z>0.5605479200716120269376574</z>
		</rotation>
	</pose>
	<pose>
		<id>00005-cam3</id>
		<translation>
			<x>-0.5440875251388397337848346</x>
			<y>0.09546773894057658527145804</y>
			<z>1.821894246330006073009145</z>
		</translation>
		<rotation>
			<w>0.6847395289542781426916918</w>
			<x>0.1753341580245167952156748</x>
			<y>-0.6853141307883751087715041</y>
			<z>0.1753118725559662527402338</z>
		</rotation>
	</pose>
	<pose>
		<id>00005-cam4</id>
		<translation>
			<x>-0.5365467336306271040058391</x>
			<y>0.450895454882495383408525</y>
			<z>1.820805795195439280576011</z>
		</translation>
		<rotation>
			<w>0.682246809643650808929749</w>
			<x>-0.190071974440440910614214</x>
			<y>-0.6795675199866177962348956</y>
			<z>-0.191311058338531736477961</z>
		</rotation>
	</pose>
	<pose>
		<id>00005-cam5</id>
		<translation>
			<x>-0.4147980178761386249597365</x>
			<y>0.2714238912279840487684623</y>
			<z>1.921154299243843954769773</z>
		</translation>
		<rotation>
			<w>0.7004405922732925837692619</w>
			<x>-0.005813089070057802891511312</x>
			<y>-0.0001522310856530075136566066</y>
			<z>-0.7136870192997744055674048</z>
		</rotation>
	</pose>
	<pose>
		<id>00006-cam0</id>
		<translation>
			<x>-0.2656410063099393092933553</x>
			<y>0.3011852553786911190769615</y>
			<z>1.811219977884073406571019</z>
		</translation>
		<rotation>
			<w>0.7085906643944741567509027</w>
			<x>0.03946176820403341639620365</x>
			<y>-0.7035190514090502444943809</y>
			<z>0.03745642171509140638807622</z>
		</rotation>
	</pose>
	<pose>
		<id>00006-cam1</id>
		<translation>
			<x>-0.1035425484446586552600422</x>
			<y>0.4532724754678934542262425</y>
			<z>1.814281236784578421605829</z>
		</translation>
		<rotation>
			<w>0.5849910683385987075766366</w>
			<x>-0.4049506550360872925153899</x>
			<y>-0.5781028144718717287631193</y>
			<z>-0.3994966244014288569985638</z>
		</rotation>
	</pose>
	<pose>
		<id>00006-cam2</id>
		<translation>
			<x>0.1175318690455297854224881</x>
			<y>0.4551471451909216980880046</y>
			<z>1.82323187412945642016382</z>
		</translation>
		<rotation>
			<w>-0.2160235232854998133067426</w>
			<x>0.6683417960218159814544947</x>
			<y>0.213959486123579400995709</y>
			<z>0.6788773228054743036352647</z>
		</rotation>
	</pose>
	<pose>
		<id>00006-cam3</id>
		<translation>
			<x>0.1786239834959982841766646</x>
			<y>0.2182976909163680256931173</y>
			<z>1.821306580812820596904089</z>
		</translation>
		<rotation>
			<w>0.2382360479696415678230181</w>
			<x>0.6650334130920075859094709</x>
			<y>-0.2307967877157604819071679</y>
			<z>0.6691091000307399783153528</z>
		</rotation>
	</pose>
	<pose>
		<id>00006-cam4</id>
		<translation>
			<x>-0.152522069751090671996252</x>
			<y>0.08895660590663159728030962</y>
			<z>1.821015565898492782892504</z>
		</translation>
		<rotation>
			<w>0.5401041095706725636560463</w>
			<x>0.455740003129051662877913</x>
			<y>-0.5331663370376937827188613</y>
			<z>0.4651045661904995576207966</z>
		</rotation>
	</pose>
	<pose>
		<id>00006-cam5</id>
		<translation>
			<x>-0.03370258619751242273876457</x>
			<y>0.2714591688964996252231288</y>
			<z>1.91938913476212680286892</z>
		</translation>
		<rotation>
			<w>0.9824282931328545132032559</w>
			<x>-0.00945474858883908926554529</x>
			<y>-0.004966942895553837049316126</y>
			<z>0.1863346078987709597551969</z>
		</rotation>
	</pose>
	<pose>
		<id>00007-cam0</id>
		<translation>
			<x>0.08253892593304176794610783</x>
			<y>-0.3142303676344007645759859</y>
			<z>1.814356280479896943447216</z>
		</translation>
		<rotation>
			<w>0.6752215556776584026721366</w>
			<x>0.2293918414065927724454497</x>
			<y>-0.6621704562507875202470586</y>
			<z>0.2301858396231298842238289</z>
		</rotation>
	</pose>
	<pose>
		<id>00007-cam1</id>
		<translation>
			<x>0.140579426331596896160292</x>
			<y>-0.0996488455820427887488222</y>
			<z>1.815725430223644076832556</z>
		</translation>
		<rotation>
			<w>0.6744199089135302083164447</w>
			<x>-0.234547649520220807817239</x>
			<y>-0.664077147695472991273391</y>
			<z>-0.2216906144255166855039363</z>
		</rotation>
	</pose>
	<pose>
		<id>00007-cam2</id>
		<translation>
			<x>0.3277729708145414866393708</x>
			<y>0.01813661359194085331836277</y>
			<z>1.822259102711258238471714</z>
		</translation>
		<rotation>
			<w>-0.3935027186345997352034942</w>
			<x>0.5883929758774563145706793</x>
			<y>0.388015546525957710777277</y>
			<z>0.5902484663979261636512774</z>
		</rotation>
	</pose>
	<pose>
		<id>00007-cam3</id>
		<translation>
			<x>0.5041691672360290032983698</x>
			<y>-0.1513054341999451046785197</y>
			<z>1.819540367362059374300998</z>
		</translation>
		<rotation>
			<w>0.04852037915461310940701267</w>
			<x>0.7060442531913126984477458</x>
			<y>-0.03832416834683043810327874</y>
			<z>0.7054633537668518750152202</z>
		</rotation>
	</pose>
	<pose>
		<id>00007-cam4</id>
		<translation>
			<x>0.2903771045482859136654952</x>
			<y>-0.4353287186467353908625455</y>
			<z>1.82280186528373477905518</z>
		</translation>
		<rotation>
			<w>0.3959713183913423639737061</w>
			<x>0.5858140237127400506977892</x>
			<y>-0.3849916098526417473912886</y>
			<z>0.593135823434100095674637</z>
		</rotation>
	</pose>
	<pose>
		<id>00007-cam5</id>
		<translation>
			<x>0.2965289667955167129953509</x>
			<y>-0.2171001485894100690998698</y>
			<z>1.919966982601513549866468</z>
		</translation>
		<rotation>
			<w>0.8942086440406461500529645</w>
			<x>-0.007961763354693861260980015</x>
			<y>-0.00189078846046708808764647</y>
			<z>0.4475756206750183263665122</z>
		</rotation>
	</pose>
</poses>
